mtmai/__init__.py
mtmai/_version.py
mtmai/main.py
mtmai/lib/__ini__.py
mtmai/lib/cftunnel.py
mtmai/lib/hf.py
mtmai/lib/mtutils.py
mtmai/lib/huggingface/1.ipynb
mtmai/lib/huggingface/1.py
mtmai/lib/huggingface/push_model.py
mtmai/my_awesome_qa_model/runs/Jul18_10-10-59_doriandarko-claudeengin-f6y8ni679uq/events.out.tfevents.1721297461.doriandarko-claudeengin-f6y8ni679uq.129166.0
mtmai/routes/__init__.py
mtmai/routes/classifyDemo1.py
mtmai/routes/completion.py
mtmai/routes/demos.py
mtmai/routes/health.py
mtmai/text_classify/__init__.py
mtmai/text_classify/art_rewrite.py
mtmai/text_classify/text_classify.py
mtmai/text_classify/data/class.txt
mtmai/text_classify/data/dev.txt
mtmai/text_classify/data/embedding_SougouNews.npz
mtmai/text_classify/data/embedding_Tencent.npz
mtmai/text_classify/data/test.txt
mtmai/text_classify/data/train.txt
mtmai/text_classify/data/vocab.pkl
mtmai/text_classify/demo1/README.md
mtmai/text_classify/demo1/RNNmodel.py
mtmai/text_classify/demo1/__init__.py
mtmai/text_classify/demo1/data_process_module.py
mtmai/text_classify/demo1/main.py
mtmai/text_classify/demo1/train_best_model.py
mtmai/text_classify/distilbert/TextClassificationWithBERT.ipynb
mtmai/text_classify/distilbert/distilbert copy.py
mtmai/text_classify/distilbert/distilbert.py
mtmai/text_classify/test_data/data1.txt
mtmai/text_classify/tests/text_classify_test.py
mtmai/video/Stable Diffusion Deep Dive.ipynb
mtmai/video/diffusion-nbs/.gitignore
mtmai/video/diffusion-nbs/README.md
mtmai/video/diffusion-nbs/Stable Diffusion Deep Dive.ipynb
mtmai/video/diffusion-nbs/learned_embeds.bin
mtmai/video/diffusion-nbs/requirements.txt
mtmai/video/diffusion-nbs/stable_diffusion.ipynb
mtmai/video/diffusion-nbs/suggested_tools.md
mtmai/video/diffusion-nbs/textual_inversion_inference.ipynb
mtmai/video/diffusion-nbs/textual_inversion_training.py
pymtlibs/_version.py
pymtlibs/slepian123/__init__.py
pymtlibs/slepian123/_array_methods.py
pymtlibs/slepian123/_bool_methods.py
pymtlibs-0.0.13.dev6.dist-info/LICENCE.txt
pymtlibs-0.0.13.dev6.dist-info/METADATA
pymtlibs-0.0.13.dev6.dist-info/WHEEL
pymtlibs-0.0.13.dev6.dist-info/entry_points.txt
pymtlibs-0.0.13.dev6.dist-info/top_level.txt
pymtlibs-0.0.13.dev6.dist-info/RECORD
