Metadata-Version: 2.1
Name: pymtlibs
Version: 0.0.13.dev6
Summary: Slepian Scale-Discretised Wavelets in Python
Author-email: "Patrick J. Roddy" <patrickjamesroddy@gmail.com>
License: BSD 3-Clause Licence
Project-URL: Code, https://github.com/astro-informatics/pymtlibs
Project-URL: Documentation, https://astro-informatics.github.io/pymtlibs
Project-URL: Download, https://pypi.org/project/pymtlibs
Project-URL: Homepage, https://github.com/astro-informatics/pymtlibs
Project-URL: Issues, https://github.com/astro-informatics/pymtlibs/issues
Keywords: manifolds,python,slepian-functions,sphere,wavelets
Classifier: License :: OSI Approved :: BSD License
Classifier: Operating System :: POSIX
Classifier: Programming Language :: Python :: 3
Classifier: Programming Language :: Python :: 3 :: Only
Classifier: Programming Language :: Python :: 3.10
Classifier: Programming Language :: Python :: 3.11
Classifier: Programming Language :: Python :: 3.12
Classifier: Topic :: Scientific/Engineering :: Image Processing
Classifier: Topic :: Scientific/Engineering :: Mathematics
Classifier: Topic :: Scientific/Engineering :: Physics
Classifier: Topic :: Scientific/Engineering :: Visualization
Classifier: Typing :: Typed
Requires-Python: >=3.10
License-File: LICENCE.txt
Requires-Dist: cmocean ~=4.0
Requires-Dist: gmpy2 ~=2.0
Requires-Dist: hypothesis ~=6.0
Requires-Dist: libigl ~=2.0
Requires-Dist: matplotlib ~=3.0
Requires-Dist: multiprocess ~=0.0
Requires-Dist: numba ~=0.0
Requires-Dist: numpy ~=1.0
Requires-Dist: platformdirs ~=4.0
Requires-Dist: plotly ~=5.0
Requires-Dist: pooch ~=1.0
Requires-Dist: pydantic ~=2.0
Requires-Dist: pys2let ~=2.0
Requires-Dist: pyssht ~=1.0
Requires-Dist: scipy ~=1.0
Requires-Dist: seaborn ~=0.0
Requires-Dist: tomli ~=2.0
Requires-Dist: tqdm ~=4.0
Requires-Dist: openai
Requires-Dist: transformers
Requires-Dist: langchain-community
Requires-Dist: langchain
Requires-Dist: langchainhub
Requires-Dist: tf-keras
Requires-Dist: beautifulsoup4
Requires-Dist: requests
Requires-Dist: chromadb
Requires-Dist: uvicorn
Requires-Dist: fastapi
Requires-Dist: inngest
Requires-Dist: huggingface-hub
Requires-Dist: pika
Requires-Dist: torch >=2.3
Requires-Dist: sentencepiece
Requires-Dist: accelerate
Requires-Dist: pandas
Requires-Dist: bitsandbytes
Requires-Dist: matplotlib
Requires-Dist: sentence-transformers
Requires-Dist: tensorflow
Requires-Dist: evaluate
Requires-Dist: datasets
Provides-Extra: dev
Requires-Dist: build ; extra == 'dev'
Requires-Dist: mypy ; extra == 'dev'
Requires-Dist: pre-commit ; extra == 'dev'
Requires-Dist: pytest ; extra == 'dev'
Requires-Dist: ruff ; extra == 'dev'
Requires-Dist: tox ; extra == 'dev'
Requires-Dist: tuna ; extra == 'dev'
Requires-Dist: twine ; extra == 'dev'
Requires-Dist: debugpy ; extra == 'dev'
Requires-Dist: pylint ; extra == 'dev'
Requires-Dist: watchdog[watchmedo] ; extra == 'dev'
Requires-Dist: jupyter ; extra == 'dev'
Requires-Dist: ipywidgets ; extra == 'dev'
Provides-Extra: docs
Requires-Dist: pdoc3 ; extra == 'docs'
Provides-Extra: readme
Requires-Dist: pytest-codeblocks ; extra == 'readme'
